llama_index/readers/s3/__init__.py
llama_index/readers/s3/base.py
llama_index_readers_s3-0.5.0.dist-info/METADATA
llama_index_readers_s3-0.5.0.dist-info/WHEEL
llama_index_readers_s3-0.5.0.dist-info/licenses/LICENSE
llama_index_readers_s3-0.5.0.dist-info/RECORD
