Metadata-Version: 2.4
Name: llama-index-readers-s3
Version: 0.5.0
Summary: llama-index readers s3 integration
Author-email: Your Name <you@example.com>
Maintainer: thejessezhang
License-Expression: MIT
License-File: LICENSE
Keywords: amazon web services,aws s3,bucket
Requires-Python: <4.0,>=3.9
Requires-Dist: llama-index-core<0.14,>=0.13.0
Requires-Dist: llama-index-readers-file<0.6,>=0.5.0
Requires-Dist: s3fs>=2024.3.1
